hashable_list/__init__.py
hashable_list/hashable_list.py
tests/__init__.py
tests/test_hashable_list.py
hashable_list-0.1.0.dist-info/LICENSE
hashable_list-0.1.0.dist-info/METADATA
hashable_list-0.1.0.dist-info/WHEEL
hashable_list-0.1.0.dist-info/top_level.txt
hashable_list-0.1.0.dist-info/RECORD
