Metadata-Version: 2.1
Name: hashable-list
Version: 0.1.0
Summary: A hashable list type in Python
Home-page: https://github.com/anton2yakovlev/hashable-list
Author: Anton Yakovlev
Author-email: anton2yakovlev@gmail.com
License: MIT
Classifier: Development Status :: 3 - Alpha
Classifier: Intended Audience :: Developers
Classifier: License :: OSI Approved :: MIT License
Classifier: Programming Language :: Python :: 3
Classifier: Programming Language :: Python :: 3.12
Requires-Python: >=3.9
License-File: LICENSE
